[
  {
    "avaliador": "joaoaosaldanha@gmail.com",
    "integrante": "joaoaos99@gmail.com",
    "sprint": 1,
    "time": 1,
    "comunicacao": 3,
    "texto_comunicacao": "qqwer",
    "engajamento": 3,
    "texto_engajamento": "qwer",
    "conhecimento": 3,
    "texto_conhecimento": "qwer",
    "entrega": 3,
    "texto_entrega": "qwer",
    "autogestao": 3,
    "texto_autogestao": "qwer"
  },
  {
    "avaliador": "joaoaos99@gmail.com",
    "integrante": "joaoaosaldanha@gmail.com",
    "sprint": 1,
    "time": 1,
    "comunicacao": 1,
    "texto_comunicacao": "1",
    "engajamento": 1,
    "texto_engajamento": "1",
    "conhecimento": 1,
    "texto_conhecimento": "1",
    "entrega": 1,
    "texto_entrega": "1",
    "autogestao": 1,
    "texto_autogestao": "1"
  },
  {
    "avaliador": "joaoaos99@gmail.com",
    "integrante": "joaoaosaldanha@gmail.com",
    "sprint": 1,
    "time": 5,
    "comunicacao": 5,
    "texto_comunicacao": "5",
    "engajamento": 5,
    "texto_engajamento": "5",
    "conhecimento": 5,
    "texto_conhecimento": "5",
    "entrega": 5,
    "texto_entrega": "5",
    "autogestao": 5,
    "texto_autogestao": "5"
  }
]