[
  {
    "index": 0,
    "turma": "bd01",
    "nome": "1 Sprint",
    "sprints": 1,
    "duracao": 7,
    "inicio": "27-05-2023",
    "fim": "02-06-2023",
    "avaliacoes": [
      [
        1,
        "03-06-2023",
        "07-06-2023"
      ]
    ]
  },
  {
    "index": 1,
    "turma": "bd02",
    "nome": "4 Sprint",
    "sprints": 1,
    "duracao": 7,
    "inicio": "27-05-2023",
    "fim": "02-06-2023",
    "avaliacoes": [
      [
        1,
        "03-06-2023",
        "07-06-2023"
      ]
    ]
  }
]